Metadata-Version: 2.1
Name: symmetric-secret-share
Version: 0.0.8
Summary: Python CLI to share secret files via github with symmetric encryption ed25519.
License: Apache-2.0
Author: Pablion
Author-email: 36828324+Pablion@users.noreply.github.com
Requires-Python: >=3.9,<4.0
Classifier: License :: OSI Approved :: Apache Software License
Classifier: Programming Language :: Python :: 3
Classifier: Programming Language :: Python :: 3.10
Classifier: Programming Language :: Python :: 3.9
Requires-Dist: PyNaCl (>=1.5.0,<2.0.0)
Requires-Dist: requests (>=2.27.1,<3.0.0)
Requires-Dist: typer[all] (>=0.4.0,<0.5.0)
Project-URL: documentation, https://github.com/PabloLION/symmetric-secret-share
Project-URL: homepage, https://github.com/PabloLION/symmetric-secret-share
Project-URL: repository, https://github.com/PabloLION/symmetric-secret-share
